printd/__init__.py
printd/printd.py
printd_Tl-0.1.dist-info/METADATA
printd_Tl-0.1.dist-info/WHEEL
printd_Tl-0.1.dist-info/top_level.txt
printd_Tl-0.1.dist-info/RECORD
