Metadata-Version: 2.1
Name: printd-Tl
Version: 0.1
Summary: A package to print experiment codes for Python.
Author: code-tl
